datapress_client/__init__.py
datapress_client-2.0.0.dist-info/METADATA
datapress_client-2.0.0.dist-info/WHEEL
datapress_client-2.0.0.dist-info/top_level.txt
datapress_client-2.0.0.dist-info/RECORD
