Metadata-Version: 2.4
Name: datapress-client
Version: 2.0.0
Summary: Deprecated package. Use 'datapress' instead.
Project-URL: Homepage, https://github.com/datapressio/datapress-client
Classifier: Development Status :: 7 - Inactive
Classifier: Intended Audience :: Developers
Classifier: Programming Language :: Python :: 3
Classifier: Programming Language :: Python :: 3.7
Classifier: Programming Language :: Python :: 3.8
Classifier: Programming Language :: Python :: 3.9
Classifier: Programming Language :: Python :: 3.10
Classifier: Programming Language :: Python :: 3.11
Classifier: Programming Language :: Python :: 3.12
Requires-Python: >=3.7
Requires-Dist: datapress
Dynamic: requires-python
